AthenaDPGLib/__init__.py
AthenaDPGLib/data/__init__.py
AthenaDPGLib/data/exceptions.py
AthenaDPGLib/data/json_ui_parser_mappings.py
AthenaDPGLib/functions/__init__.py
AthenaDPGLib/functions/cleanups.py
AthenaDPGLib/functions/fixes.py
AthenaDPGLib/functions/json_ui_parser.py
AthenaDPGLib/models/__init__.py
AthenaDPGLib/models/custom_callbacks.py
AthenaDPGLib/models/athena_application/__init__.py
AthenaDPGLib/models/athena_application/athena_application.py
AthenaDPGLib/models/athena_application/sub_systems/__init__.py
AthenaDPGLib/models/athena_application/sub_systems/custom_callbacks.py
AthenaDPGLib/models/athena_application/sub_systems/json_ui_parser.py
AthenaDPGLib/models/json_ui_parser/__init__.py
AthenaDPGLib/models/json_ui_parser/custom_dpg_items.py
AthenaDPGLib/models/json_ui_parser/custom_dpg_items_premade.py
AthenaDPGLib-0.3.0.dist-info/LICENSE
AthenaDPGLib-0.3.0.dist-info/METADATA
AthenaDPGLib-0.3.0.dist-info/WHEEL
AthenaDPGLib-0.3.0.dist-info/top_level.txt
AthenaDPGLib-0.3.0.dist-info/RECORD
