Metadata-Version: 2.1
Name: AthenaDPGLib
Version: 0.3.0
Summary: A Library of OOP DearPyGui elements, to be used in Directive Athena projects
Home-page: https://github.com/DirectiveAthena/AthenaDPGLib
Author: Andreas Sas
Author-email: 
License: GPLv3
Project-URL: Bug Tracker, https://github.com/DirectiveAthena/AthenaDPGLib/issues
Requires-Python: >=3.10
License-File: LICENSE
Requires-Dist: DearPyGui (>=1.6.2)
Requires-Dist: AthenaLib (>=1.6.2)
Requires-Dist: AthenaColor (>=6.2.0)
